speculate/__init__.py
speculate/cli/__init__.py
speculate/cli/cli_commands.py
speculate/cli/cli_main.py
speculate/cli/cli_ui.py
speculate/cli/resources/__init__.py
speculate/cli/resources/claude-hooks/__init__.py
speculate/cli/resources/claude-hooks/hooks.json
speculate/cli/resources/claude-hooks/scripts/__init__.py
speculate/cli/resources/claude-hooks/scripts/ensure-gh-cli.sh
speculate/cli/resources/claude-hooks/scripts/ensure-tbd-cli.sh
speculate_cli-0.0.11.dist-info/METADATA
speculate_cli-0.0.11.dist-info/WHEEL
speculate_cli-0.0.11.dist-info/entry_points.txt
speculate_cli-0.0.11.dist-info/RECORD
